vanadis/__init__.py
vanadis/colormap.py
vanadis-0.0.2.dist-info/LICENSE
vanadis-0.0.2.dist-info/METADATA
vanadis-0.0.2.dist-info/WHEEL
vanadis-0.0.2.dist-info/top_level.txt
vanadis-0.0.2.dist-info/RECORD
