Metadata-Version: 2.1
Name: vanadis
Version: 0.0.2
Summary: UNKNOWN
Home-page: UNKNOWN
Author: UNKNOWN
Author-email: UNKNOWN
License: MIT Licence
Platform: UNKNOWN
Requires-Dist: matplotlib
